<?xml version="1.0" encoding="UTF-8"?>
<!DOCTYPE netconf SYSTEM "netconf.dtd">
<netconf>
  <links>
    <maxTime>1</maxTime>
    <minTime>1</minTime>
  </links>
  <flows>
    <flow id="f1">
      <priority>10</priority>
      <deadline>36</deadline>
      <!-- La pérode est optionnelle, si elle n'est pas spécifié
           elle est égale à la deadline -->
      <period>36</period>
      <!-- Si le jitter n'est pas déclaré, il est égal à 0-->
      <jitter>0</jitter>
      <path>
        <node id="n1">
        	<capacity>4</capacity>
        </node>
        <node id="n3">
        	<capacity>4</capacity>
        </node>
        <node id="n4">
        	<capacity>4</capacity>
        </node>
        <node id="n5">
        	<capacity>4</capacity>
        </node>
      </path>
    </flow>
    <flow id="f2">
      <priority>10</priority>
      <deadline>36</deadline>
      <period>36</period>
      <path>
        <node id="n9">
        	<capacity>4</capacity>
        </node>
        <node id="n10">
        	<capacity>4</capacity>
        </node>
        <node id="n7">
        	<capacity>4</capacity>
        </node>
        <node id="n6">
        	<capacity>4</capacity>
        </node>
      </path>
    </flow>
    <flow id="f3">
      <priority>11</priority>
      <deadline>54</deadline>
      <period>36</period>
      <path>
        <node id="n2">
        	<capacity>4</capacity>
        </node>
        <node id="n3">
        	<capacity>4</capacity>
        </node>
        <node id="n4">
        	<capacity>4</capacity>
        </node>
        <node id="n7">
        	<capacity>4</capacity>
        </node>
        <node id="n10">
        	<capacity>4</capacity>
        </node>
        <node id="n11">
	        <capacity>4</capacity>
        </node>
      </path>
    </flow>
    <flow id="f4">
      <priority>11</priority>
      <deadline>54</deadline>
      <period>36</period>
      <path>
      	<node id="n2">
      		<capacity>4</capacity>
        </node>
        <node id="n3">
        	<capacity>4</capacity>
        </node>
        <node id="n4">
        	<capacity>4</capacity>
        </node>
        <node id="n7">
        	<capacity>4</capacity>
        </node>
        <node id="n10">
        	<capacity>4</capacity>
        </node>
        <node id="n11">
        	<capacity>4</capacity>
        </node>
      </path>
    </flow>
    <flow id="f5">
      <priority>12</priority>
      <deadline>45</deadline>
      <period>36</period>
      <path>
    	<node id="n2">
    		<capacity>4</capacity>
        </node>
        <node id="n3">
        	<capacity>4</capacity>
        </node>
        <node id="n4">
        	<capacity>4</capacity>
        </node>
        <node id="n7">
        	<capacity>4</capacity>
        </node>
        <node id="n8">
        	<capacity>4</capacity>
        </node>
      </path>
    </flow>
  </flows>
</netconf>
